<?xml version="1.0" encoding="utf-8"?>
<AssetDeclaration xmlns="uri:ea.com:eala:asset" xmlns:xsi="http://www.w3.org/2001/XMLSchema-instance" xmlns:xi="http://www.w3.org/2001/XInclude">
	<Tags></Tags>
	<Includes>
		<Include type="all" source="DATA:GlobalData/GlobalDefines.xml" />
	</Includes>
<GameObject
	id="BaseUnitBuild"
	Side="Allies"
	EditorSorting="SYSTEM"
	KindOf="STRUCTURE IGNORE_FOR_VICTORY IMMOBILE IGNORES_SELECT_ALL INERT SKIRMISH_AI_DONT_CONSIDER_THREAT DONT_DESTROY_IF_ON_BRIDGE IGNORE_IN_AI_HUNT_TACTIC UNATTACKABLE POWERED"
	RadarPriority="NOT_ON_RADAR">
	<ArmorSet
		Armor="NoArmor"/>
	<Draws>
		<ScriptedModelDraw
			id="ModuleTag_Draw"
			OkToChangeModelColor="true">
			<ModelConditionState
				ParseCondStateType="PARSE_DEFAULT">
				<Model
					Name="" />
			</ModelConditionState>
		</ScriptedModelDraw>
	</Draws>
	<Behaviors>
		<DestroyDie
			id="ModuleTag_Die">
			<DieMuxData
				DeathTypes="ALL"/>
		</DestroyDie>
		<FireWeaponUpdate
			id="ModuleTag_FireWeaponUpdate"
			AliveOnly="true">
			<FireWeaponNugget
				WeaponName="DamageSelfAlliedWarFactoryWarhead"
				OneShot="true" />
		</FireWeaponUpdate>
	</Behaviors>
	<AI>
		<AIUpdate
			id="ModuleTag_AI"
			AutoAcquireEnemiesWhenIdle="NO">
		</AIUpdate>
	</AI>
	<Body>
		<PropBody
			id="ModuleTag_Body"/>
	</Body>
	<VisionInfo
		VisionRange="0"
		ShroudClearingRange="0" />
</GameObject>

<GameObject
	id="ModuleTag_SpecialAbilityUpdate1"
		inheritFrom="BaseUnitBuild">
	<Behaviors>
		<SpecialPower
				 id="ModuleTag_SpecialAbility"
				 SpecialPowerTemplate="SpecialPower_AlliedAntiAirVehicleTech1"
				 AvailableAtStart="true"
				 UpdateModuleStartsAttack="true"/>
		<WeaponFireSpecialAbilityUpdate
			id="ModuleTag_SpecialAbilityUpdate"
			SpecialPowerTemplate="SpecialPower_AlliedAntiAirVehicleTech1"
			SpecialWeapon="SpecialPower_AlliedAntiAirVehicleTech1Weapon"/>
	</Behaviors>
</GameObject>
	<WeaponTemplate
		id="SpecialPower_AlliedAntiAirVehicleTech1Weapon"
		RadiusDamageAffects="ALLIES"
        Flags="NOT_ATTRACTED_BY_MAGNETS"
		RequiredAntiMask="ANTI_STRUCTURE">
		<Nuggets>
			<AttributeModifierNugget
			Radius="50.0"
			AttributeModifierName="SpecialPower_AlliedAntiAirVehicleTech1">
				<SpecialObjectFilter
					Rule="ANY"
					Relationship="SAME_PLAYER">
					<IncludeThing>AlliedWarFactory</IncludeThing>
				</SpecialObjectFilter>
			</AttributeModifierNugget>
		</Nuggets>
	</WeaponTemplate>
	<ObjectCreationList
		id="OCL_ModuleTag_SpecialAbilityUpdate1">
		<CreateObject
			Options="IGNORE_ALL_OBJECTS DO_NOT_COPY_SHADERS"
			Disposition="ON_GROUND_ALIGNED USE_WATER_SURFACE">
			<CreateObject>ModuleTag_SpecialAbilityUpdate1</CreateObject>
		</CreateObject>
	</ObjectCreationList>
	
	<GameObject
		id="ModuleTag_SpecialAbilityUpdate2"
			inheritFrom="BaseUnitBuild">
		<Behaviors>
			<SpecialPower
					 id="ModuleTag_SpecialAbility"
					 SpecialPowerTemplate="SpecialPower_JapanAntiVehicleVehicleTech1"
					 AvailableAtStart="true"
					 UpdateModuleStartsAttack="true"/>
			<WeaponFireSpecialAbilityUpdate
				id="ModuleTag_SpecialAbilityUpdate"
				SpecialPowerTemplate="SpecialPower_JapanAntiVehicleVehicleTech1"
				SpecialWeapon="SpecialPower_JapanAntiVehicleVehicleTech1Weapon"/>
		</Behaviors>
	</GameObject>
	<WeaponTemplate
		id="SpecialPower_JapanAntiVehicleVehicleTech1Weapon"
		RadiusDamageAffects="ALLIES"
        Flags="NOT_ATTRACTED_BY_MAGNETS"
		RequiredAntiMask="ANTI_STRUCTURE">
		<Nuggets>
			<AttributeModifierNugget
			Radius="50.0"
			AttributeModifierName="SpecialPower_JapanAntiVehicleVehicleTech1">
				<SpecialObjectFilter
					Rule="ANY"
					Relationship="SAME_PLAYER">
					<IncludeThing>AlliedWarFactory</IncludeThing>
				</SpecialObjectFilter>
			</AttributeModifierNugget>
		</Nuggets>
	</WeaponTemplate>
	<ObjectCreationList
		id="OCL_ModuleTag_SpecialAbilityUpdate2">
		<CreateObject
			Options="IGNORE_ALL_OBJECTS DO_NOT_COPY_SHADERS"
			Disposition="ON_GROUND_ALIGNED USE_WATER_SURFACE">
			<CreateObject>ModuleTag_SpecialAbilityUpdate2</CreateObject>
		</CreateObject>
	</ObjectCreationList>
	
	<GameObject
		id="ModuleTag_SpecialAbilityUpdate3"
			inheritFrom="BaseUnitBuild">
		<Behaviors>
			<SpecialPower
					 id="ModuleTag_SpecialAbility"
					 SpecialPowerTemplate="SpecialPower_SovietAntiVehicleVehicleTech1"
					 AvailableAtStart="true"
					 UpdateModuleStartsAttack="true"/>
			<WeaponFireSpecialAbilityUpdate
				id="ModuleTag_SpecialAbilityUpdate"
				SpecialPowerTemplate="SpecialPower_SovietAntiVehicleVehicleTech1"
				SpecialWeapon="SpecialPower_SovietAntiVehicleVehicleTech1Weapon"/>
		</Behaviors>
	</GameObject>
	<WeaponTemplate
		id="SpecialPower_SovietAntiVehicleVehicleTech1Weapon"
		RadiusDamageAffects="ALLIES"
        Flags="NOT_ATTRACTED_BY_MAGNETS"
		RequiredAntiMask="ANTI_STRUCTURE">
		<Nuggets>
			<AttributeModifierNugget
			Radius="50.0"
			AttributeModifierName="SpecialPower_SovietAntiVehicleVehicleTech1">
				<SpecialObjectFilter
					Rule="ANY"
					Relationship="SAME_PLAYER">
					<IncludeThing>AlliedWarFactory</IncludeThing>
				</SpecialObjectFilter>
			</AttributeModifierNugget>
		</Nuggets>
	</WeaponTemplate>
	<ObjectCreationList
		id="OCL_ModuleTag_SpecialAbilityUpdate3">
		<CreateObject
			Options="IGNORE_ALL_OBJECTS DO_NOT_COPY_SHADERS"
			Disposition="ON_GROUND_ALIGNED USE_WATER_SURFACE">
			<CreateObject>ModuleTag_SpecialAbilityUpdate3</CreateObject>
		</CreateObject>
	</ObjectCreationList>
	
	<GameObject
		id="ModuleTag_SpecialAbilityUpdate4"
			inheritFrom="BaseUnitBuild">
		<Behaviors>
			<SpecialPower
					 id="ModuleTag_SpecialAbility"
					 SpecialPowerTemplate="SpecialPower_AlliedAntiVehicleVehicleTech1"
					 AvailableAtStart="true"
					 UpdateModuleStartsAttack="true"/>
			<WeaponFireSpecialAbilityUpdate
				id="ModuleTag_SpecialAbilityUpdate"
				SpecialPowerTemplate="SpecialPower_AlliedAntiVehicleVehicleTech1"
				SpecialWeapon="SpecialPower_AlliedAntiVehicleVehicleTech1Weapon"/>
		</Behaviors>
	</GameObject>
	<WeaponTemplate
		id="SpecialPower_AlliedAntiVehicleVehicleTech1Weapon"
		RadiusDamageAffects="ALLIES"
        Flags="NOT_ATTRACTED_BY_MAGNETS"
		RequiredAntiMask="ANTI_STRUCTURE">
		<Nuggets>
			<AttributeModifierNugget
			Radius="50.0"
			AttributeModifierName="SpecialPower_AlliedAntiVehicleVehicleTech1">
				<SpecialObjectFilter
					Rule="ANY"
					Relationship="SAME_PLAYER">
					<IncludeThing>AlliedWarFactory</IncludeThing>
				</SpecialObjectFilter>
			</AttributeModifierNugget>
		</Nuggets>
	</WeaponTemplate>
	<ObjectCreationList
		id="OCL_ModuleTag_SpecialAbilityUpdate4">
		<CreateObject
			Options="IGNORE_ALL_OBJECTS DO_NOT_COPY_SHADERS"
			Disposition="ON_GROUND_ALIGNED USE_WATER_SURFACE">
			<CreateObject>ModuleTag_SpecialAbilityUpdate4</CreateObject>
		</CreateObject>
	</ObjectCreationList>
	
	<GameObject
		id="ModuleTag_SpecialAbilityUpdate5"
			inheritFrom="BaseUnitBuild">
		<Behaviors>
			<SpecialPower
					 id="ModuleTag_SpecialAbility"
					 SpecialPowerTemplate="SpecialPower_JapanAntiVehicleVehicleTech3"
					 AvailableAtStart="true"
					 UpdateModuleStartsAttack="true"/>
			<WeaponFireSpecialAbilityUpdate
				id="ModuleTag_SpecialAbilityUpdate"
				SpecialPowerTemplate="SpecialPower_JapanAntiVehicleVehicleTech3"
				SpecialWeapon="SpecialPower_JapanAntiVehicleVehicleTech3Weapon"/>
		</Behaviors>
	</GameObject>
	<WeaponTemplate
		id="SpecialPower_JapanAntiVehicleVehicleTech3Weapon"
		RadiusDamageAffects="ALLIES"
        Flags="NOT_ATTRACTED_BY_MAGNETS"
		RequiredAntiMask="ANTI_STRUCTURE">
		<Nuggets>
			<AttributeModifierNugget
			Radius="50.0"
			AttributeModifierName="SpecialPower_JapanAntiVehicleVehicleTech3">
				<SpecialObjectFilter
					Rule="ANY"
					Relationship="SAME_PLAYER">
					<IncludeThing>AlliedWarFactory</IncludeThing>
				</SpecialObjectFilter>
			</AttributeModifierNugget>
		</Nuggets>
	</WeaponTemplate>
	<ObjectCreationList
		id="OCL_ModuleTag_SpecialAbilityUpdate5">
		<CreateObject
			Options="IGNORE_ALL_OBJECTS DO_NOT_COPY_SHADERS"
			Disposition="ON_GROUND_ALIGNED USE_WATER_SURFACE">
			<CreateObject>ModuleTag_SpecialAbilityUpdate5</CreateObject>
		</CreateObject>
	</ObjectCreationList>
	
	<GameObject
		id="ModuleTag_SpecialAbilityUpdate6"
			inheritFrom="BaseUnitBuild">
		<Behaviors>
			<SpecialPower
					 id="ModuleTag_SpecialAbility"
					 SpecialPowerTemplate="SpecialPower_SovietAntiStructureVehicle"
					 AvailableAtStart="true"
					 UpdateModuleStartsAttack="true"/>
			<WeaponFireSpecialAbilityUpdate
				id="ModuleTag_SpecialAbilityUpdate"
				SpecialPowerTemplate="SpecialPower_SovietAntiStructureVehicle"
				SpecialWeapon="SpecialPower_SovietAntiStructureVehicleWeapon"/>
		</Behaviors>
	</GameObject>
	<WeaponTemplate
		id="SpecialPower_SovietAntiStructureVehicleWeapon"
		RadiusDamageAffects="ALLIES"
        Flags="NOT_ATTRACTED_BY_MAGNETS"
		RequiredAntiMask="ANTI_STRUCTURE">
		<Nuggets>
			<AttributeModifierNugget
			Radius="50.0"
			AttributeModifierName="SpecialPower_SovietAntiStructureVehicle">
				<SpecialObjectFilter
					Rule="ANY"
					Relationship="SAME_PLAYER">
					<IncludeThing>AlliedWarFactory</IncludeThing>
				</SpecialObjectFilter>
			</AttributeModifierNugget>
		</Nuggets>
	</WeaponTemplate>
	<ObjectCreationList
		id="OCL_ModuleTag_SpecialAbilityUpdate6">
		<CreateObject
			Options="IGNORE_ALL_OBJECTS DO_NOT_COPY_SHADERS"
			Disposition="ON_GROUND_ALIGNED USE_WATER_SURFACE">
			<CreateObject>ModuleTag_SpecialAbilityUpdate6</CreateObject>
		</CreateObject>
	</ObjectCreationList>
	
	<GameObject
		id="ModuleTag_SpecialAbilityUpdate7"
			inheritFrom="BaseUnitBuild">
		<Behaviors>
			<SpecialPower
					 id="ModuleTag_SpecialAbility"
					 SpecialPowerTemplate="SpecialPower_AlliedFighterAircraft"
					 AvailableAtStart="true"
					 UpdateModuleStartsAttack="true"/>
			<WeaponFireSpecialAbilityUpdate
				id="ModuleTag_SpecialAbilityUpdate"
				SpecialPowerTemplate="SpecialPower_AlliedFighterAircraft"
				SpecialWeapon="SpecialPower_AlliedFighterAircraftWeapon"/>
		</Behaviors>
	</GameObject>
	<WeaponTemplate
		id="SpecialPower_AlliedFighterAircraftWeapon"
		RadiusDamageAffects="ALLIES"
        Flags="NOT_ATTRACTED_BY_MAGNETS"
		RequiredAntiMask="ANTI_STRUCTURE">
		<Nuggets>
			<AttributeModifierNugget
			Radius="50.0"
			AttributeModifierName="SpecialPower_AlliedFighterAircraft">
				<SpecialObjectFilter
					Rule="ANY"
					Relationship="SAME_PLAYER">
					<IncludeThing>AlliedWarFactory</IncludeThing>
				</SpecialObjectFilter>
			</AttributeModifierNugget>
		</Nuggets>
	</WeaponTemplate>
	<ObjectCreationList
		id="OCL_ModuleTag_SpecialAbilityUpdate7">
		<CreateObject
			Options="IGNORE_ALL_OBJECTS DO_NOT_COPY_SHADERS"
			Disposition="ON_GROUND_ALIGNED USE_WATER_SURFACE">
			<CreateObject>ModuleTag_SpecialAbilityUpdate7</CreateObject>
		</CreateObject>
	</ObjectCreationList>
	
	<GameObject
		id="ModuleTag_SpecialAbilityUpdate8"
			inheritFrom="BaseUnitBuild">
		<Behaviors>
			<SpecialPower
					 id="ModuleTag_SpecialAbility"
					 SpecialPowerTemplate="SpecialPower_JapanLightTransportVehicle"
					 AvailableAtStart="true"
					 UpdateModuleStartsAttack="true"/>
			<WeaponFireSpecialAbilityUpdate
				id="ModuleTag_SpecialAbilityUpdate"
				SpecialPowerTemplate="SpecialPower_JapanLightTransportVehicle"
				SpecialWeapon="SpecialPower_JapanLightTransportVehicleWeapon"/>
		</Behaviors>
	</GameObject>
	<WeaponTemplate
		id="SpecialPower_JapanLightTransportVehicleWeapon"
		RadiusDamageAffects="ALLIES"
        Flags="NOT_ATTRACTED_BY_MAGNETS"
		RequiredAntiMask="ANTI_STRUCTURE">
		<Nuggets>
			<AttributeModifierNugget
			Radius="50.0"
			AttributeModifierName="SpecialPower_JapanLightTransportVehicle">
				<SpecialObjectFilter
					Rule="ANY"
					Relationship="SAME_PLAYER">
					<IncludeThing>AlliedWarFactory</IncludeThing>
				</SpecialObjectFilter>
			</AttributeModifierNugget>
		</Nuggets>
	</WeaponTemplate>
	<ObjectCreationList
		id="OCL_ModuleTag_SpecialAbilityUpdate8">
		<CreateObject
			Options="IGNORE_ALL_OBJECTS DO_NOT_COPY_SHADERS"
			Disposition="ON_GROUND_ALIGNED USE_WATER_SURFACE">
			<CreateObject>ModuleTag_SpecialAbilityUpdate8</CreateObject>
		</CreateObject>
	</ObjectCreationList>
	
	<GameObject
		id="ModuleTag_SpecialAbilityUpdate9"
			inheritFrom="BaseUnitBuild">
		<Behaviors>
			<SpecialPower
					 id="ModuleTag_SpecialAbility"
					 SpecialPowerTemplate="SpecialPower_SovietScoutVehicle"
					 AvailableAtStart="true"
					 UpdateModuleStartsAttack="true"/>
			<WeaponFireSpecialAbilityUpdate
				id="ModuleTag_SpecialAbilityUpdate"
				SpecialPowerTemplate="SpecialPower_SovietScoutVehicle"
				SpecialWeapon="SpecialPower_SovietScoutVehicleWeapon"/>
		</Behaviors>
	</GameObject>
	<WeaponTemplate
		id="SpecialPower_SovietScoutVehicleWeapon"
		RadiusDamageAffects="ALLIES"
        Flags="NOT_ATTRACTED_BY_MAGNETS"
		RequiredAntiMask="ANTI_STRUCTURE">
		<Nuggets>
			<AttributeModifierNugget
			Radius="50.0"
			AttributeModifierName="SpecialPower_SovietScoutVehicle">
				<SpecialObjectFilter
					Rule="ANY"
					Relationship="SAME_PLAYER">
					<IncludeThing>AlliedWarFactory</IncludeThing>
				</SpecialObjectFilter>
			</AttributeModifierNugget>
		</Nuggets>
	</WeaponTemplate>
	<ObjectCreationList
		id="OCL_ModuleTag_SpecialAbilityUpdate9">
		<CreateObject
			Options="IGNORE_ALL_OBJECTS DO_NOT_COPY_SHADERS"
			Disposition="ON_GROUND_ALIGNED USE_WATER_SURFACE">
			<CreateObject>ModuleTag_SpecialAbilityUpdate9</CreateObject>
		</CreateObject>
	</ObjectCreationList>

	<GameObject
		id="ModuleTag_SpecialAbilityUpdate10"
			inheritFrom="BaseUnitBuild">
		<Behaviors>
			<SpecialPower
					 id="ModuleTag_SpecialAbility"
					 SpecialPowerTemplate="SpecialPower_AlliedSupportAircraft"
					 AvailableAtStart="true"
					 UpdateModuleStartsAttack="true"/>
			<WeaponFireSpecialAbilityUpdate
				id="ModuleTag_SpecialAbilityUpdate"
				SpecialPowerTemplate="SpecialPower_AlliedSupportAircraft"
				SpecialWeapon="SpecialPower_AlliedSupportAircraftWeapon"/>
		</Behaviors>
	</GameObject>
	<WeaponTemplate
		id="SpecialPower_AlliedSupportAircraftWeapon"
		RadiusDamageAffects="ALLIES"
        Flags="NOT_ATTRACTED_BY_MAGNETS"
		RequiredAntiMask="ANTI_STRUCTURE">
		<Nuggets>
			<AttributeModifierNugget
			Radius="50.0"
			AttributeModifierName="SpecialPower_AlliedSupportAircraft">
				<SpecialObjectFilter
					Rule="ANY"
					Relationship="SAME_PLAYER">
					<IncludeThing>AlliedWarFactory</IncludeThing>
				</SpecialObjectFilter>
			</AttributeModifierNugget>
		</Nuggets>
	</WeaponTemplate>
	<ObjectCreationList
		id="OCL_ModuleTag_SpecialAbilityUpdate10">
		<CreateObject
			Options="IGNORE_ALL_OBJECTS DO_NOT_COPY_SHADERS"
			Disposition="ON_GROUND_ALIGNED USE_WATER_SURFACE">
			<CreateObject>ModuleTag_SpecialAbilityUpdate10</CreateObject>
		</CreateObject>
	</ObjectCreationList>
	
	<GameObject
		id="ModuleTag_SpecialAbilityUpdate11"
			inheritFrom="BaseUnitBuild">
		<Behaviors>
			<SpecialPower
					 id="ModuleTag_SpecialAbility"
					 SpecialPowerTemplate="SpecialPower_JapanAntiVehicleInfantryTech3"
					 AvailableAtStart="true"
					 UpdateModuleStartsAttack="true"/>
			<WeaponFireSpecialAbilityUpdate
				id="ModuleTag_SpecialAbilityUpdate"
				SpecialPowerTemplate="SpecialPower_JapanAntiVehicleInfantryTech3"
				SpecialWeapon="SpecialPower_JapanAntiVehicleInfantryTech3Weapon"/>
		</Behaviors>
	</GameObject>
	<WeaponTemplate
		id="SpecialPower_JapanAntiVehicleInfantryTech3Weapon"
		RadiusDamageAffects="ALLIES"
        Flags="NOT_ATTRACTED_BY_MAGNETS"
		RequiredAntiMask="ANTI_STRUCTURE">
		<Nuggets>
			<AttributeModifierNugget
			Radius="50.0"
			AttributeModifierName="SpecialPower_JapanAntiVehicleInfantryTech3">
				<SpecialObjectFilter
					Rule="ANY"
					Relationship="SAME_PLAYER">
					<IncludeThing>AlliedWarFactory</IncludeThing>
				</SpecialObjectFilter>
			</AttributeModifierNugget>
		</Nuggets>
	</WeaponTemplate>
	<ObjectCreationList
		id="OCL_ModuleTag_SpecialAbilityUpdate11">
		<CreateObject
			Options="IGNORE_ALL_OBJECTS DO_NOT_COPY_SHADERS"
			Disposition="ON_GROUND_ALIGNED USE_WATER_SURFACE">
			<CreateObject>ModuleTag_SpecialAbilityUpdate11</CreateObject>
		</CreateObject>
	</ObjectCreationList>
	
	<GameObject
		id="ModuleTag_SpecialAbilityUpdate12"
			inheritFrom="BaseUnitBuild">
		<Behaviors>
			<SpecialPower
					 id="ModuleTag_SpecialAbility"
					 SpecialPowerTemplate="SpecialPower_SovietAntiGroundAircraft"
					 AvailableAtStart="true"
					 UpdateModuleStartsAttack="true"/>
			<WeaponFireSpecialAbilityUpdate
				id="ModuleTag_SpecialAbilityUpdate"
				SpecialPowerTemplate="SpecialPower_SovietAntiGroundAircraft"
				SpecialWeapon="SpecialPower_SovietAntiGroundAircraftWeapon"/>
		</Behaviors>
	</GameObject>
	<WeaponTemplate
		id="SpecialPower_SovietAntiGroundAircraftWeapon"
		RadiusDamageAffects="ALLIES"
        Flags="NOT_ATTRACTED_BY_MAGNETS"
		RequiredAntiMask="ANTI_STRUCTURE">
		<Nuggets>
			<AttributeModifierNugget
			Radius="50.0"
			AttributeModifierName="SpecialPower_SovietAntiGroundAircraft">
				<SpecialObjectFilter
					Rule="ANY"
					Relationship="SAME_PLAYER">
					<IncludeThing>AlliedWarFactory</IncludeThing>
				</SpecialObjectFilter>
			</AttributeModifierNugget>
		</Nuggets>
	</WeaponTemplate>
	<ObjectCreationList
		id="OCL_ModuleTag_SpecialAbilityUpdate12">
		<CreateObject
			Options="IGNORE_ALL_OBJECTS DO_NOT_COPY_SHADERS"
			Disposition="ON_GROUND_ALIGNED USE_WATER_SURFACE">
			<CreateObject>ModuleTag_SpecialAbilityUpdate12</CreateObject>
		</CreateObject>
	</ObjectCreationList>
	
	<GameObject
		id="ModuleTag_SpecialAbilityUpdate13"
			inheritFrom="BaseUnitBuild">
		<Behaviors>
			<SpecialPower
					 id="ModuleTag_SpecialAbility"
					 SpecialPowerTemplate="SpecialPower_SovietBomberAircraft"
					 AvailableAtStart="true"
					 UpdateModuleStartsAttack="true"/>
			<WeaponFireSpecialAbilityUpdate
				id="ModuleTag_SpecialAbilityUpdate"
				SpecialPowerTemplate="SpecialPower_SovietBomberAircraft"
				SpecialWeapon="SpecialPower_SovietBomberAircraftWeapon"/>
		</Behaviors>
	</GameObject>
	<WeaponTemplate
		id="SpecialPower_SovietBomberAircraftWeapon"
		RadiusDamageAffects="ALLIES"
        Flags="NOT_ATTRACTED_BY_MAGNETS"
		RequiredAntiMask="ANTI_STRUCTURE">
		<Nuggets>
			<AttributeModifierNugget
			Radius="50.0"
			AttributeModifierName="SpecialPower_SovietBomberAircraft">
				<SpecialObjectFilter
					Rule="ANY"
					Relationship="SAME_PLAYER">
					<IncludeThing>AlliedWarFactory</IncludeThing>
				</SpecialObjectFilter>
			</AttributeModifierNugget>
		</Nuggets>
	</WeaponTemplate>
	<ObjectCreationList
		id="OCL_ModuleTag_SpecialAbilityUpdate13">
		<CreateObject
			Options="IGNORE_ALL_OBJECTS DO_NOT_COPY_SHADERS"
			Disposition="ON_GROUND_ALIGNED USE_WATER_SURFACE">
			<CreateObject>ModuleTag_SpecialAbilityUpdate13</CreateObject>
		</CreateObject>
	</ObjectCreationList>

	<GameObject
		id="ModuleTag_SpecialAbilityUpdate14"
			inheritFrom="BaseUnitBuild">
		<Behaviors>
			<SpecialPower
					 id="ModuleTag_SpecialAbility"
					 SpecialPowerTemplate="SpecialPower_JapanCommandoTech1"
					 AvailableAtStart="true"
					 UpdateModuleStartsAttack="true"/>
			<WeaponFireSpecialAbilityUpdate
				id="ModuleTag_SpecialAbilityUpdate"
				SpecialPowerTemplate="SpecialPower_JapanCommandoTech1"
				SpecialWeapon="SpecialPower_JapanCommandoTech1Weapon"/>
		</Behaviors>
	</GameObject>
	<WeaponTemplate
		id="SpecialPower_JapanCommandoTech1Weapon"
		RadiusDamageAffects="ALLIES"
        Flags="NOT_ATTRACTED_BY_MAGNETS"
		RequiredAntiMask="ANTI_STRUCTURE">
		<Nuggets>
			<AttributeModifierNugget
			Radius="50.0"
			AttributeModifierName="SpecialPower_JapanCommandoTech1">
				<SpecialObjectFilter
					Rule="ANY"
					Relationship="SAME_PLAYER">
					<IncludeThing>AlliedWarFactory</IncludeThing>
				</SpecialObjectFilter>
			</AttributeModifierNugget>
		</Nuggets>
	</WeaponTemplate>
	<ObjectCreationList
		id="OCL_ModuleTag_SpecialAbilityUpdate14">
		<CreateObject
			Options="IGNORE_ALL_OBJECTS DO_NOT_COPY_SHADERS"
			Disposition="ON_GROUND_ALIGNED USE_WATER_SURFACE">
			<CreateObject>ModuleTag_SpecialAbilityUpdate14</CreateObject>
		</CreateObject>
	</ObjectCreationList>

	<GameObject
		id="ModuleTag_SpecialAbilityUpdate15"
			inheritFrom="BaseUnitBuild">
		<Behaviors>
			<SpecialPower
					 id="ModuleTag_SpecialAbility"
					 SpecialPowerTemplate="SpecialPower_AlliedAntiVehicleVehicleTech3"
					 AvailableAtStart="true"
					 UpdateModuleStartsAttack="true"/>
			<WeaponFireSpecialAbilityUpdate
				id="ModuleTag_SpecialAbilityUpdate"
				SpecialPowerTemplate="SpecialPower_AlliedAntiVehicleVehicleTech3"
				SpecialWeapon="SpecialPower_AlliedAntiVehicleVehicleTech3Weapon"/>
		</Behaviors>
	</GameObject>
	<WeaponTemplate
		id="SpecialPower_AlliedAntiVehicleVehicleTech3Weapon"
		RadiusDamageAffects="ALLIES"
        Flags="NOT_ATTRACTED_BY_MAGNETS"
		RequiredAntiMask="ANTI_STRUCTURE">
		<Nuggets>
			<AttributeModifierNugget
			Radius="50.0"
			AttributeModifierName="SpecialPower_AlliedAntiVehicleVehicleTech3">
				<SpecialObjectFilter
					Rule="ANY"
					Relationship="SAME_PLAYER">
					<IncludeThing>AlliedWarFactory</IncludeThing>
				</SpecialObjectFilter>
			</AttributeModifierNugget>
		</Nuggets>
	</WeaponTemplate>
	<ObjectCreationList
		id="OCL_ModuleTag_SpecialAbilityUpdate15">
		<CreateObject
			Options="IGNORE_ALL_OBJECTS DO_NOT_COPY_SHADERS"
			Disposition="ON_GROUND_ALIGNED USE_WATER_SURFACE">
			<CreateObject>ModuleTag_SpecialAbilityUpdate15</CreateObject>
		</CreateObject>
	</ObjectCreationList>

	<GameObject
		id="ModuleTag_SpecialAbilityUpdate16"
			inheritFrom="BaseUnitBuild">
		<Behaviors>
			<SpecialPower
					 id="ModuleTag_SpecialAbility"
					 SpecialPowerTemplate="SpecialPower_AlliedAntiNavyShipTech1"
					 AvailableAtStart="true"
					 UpdateModuleStartsAttack="true"/>
			<WeaponFireSpecialAbilityUpdate
				id="ModuleTag_SpecialAbilityUpdate"
				SpecialPowerTemplate="SpecialPower_AlliedAntiNavyShipTech1"
				SpecialWeapon="SpecialPower_AlliedAntiNavyShipTech1Weapon"/>
		</Behaviors>
	</GameObject>
	<WeaponTemplate
		id="SpecialPower_AlliedAntiNavyShipTech1Weapon"
		RadiusDamageAffects="ALLIES"
        Flags="NOT_ATTRACTED_BY_MAGNETS"
		RequiredAntiMask="ANTI_STRUCTURE">
		<Nuggets>
			<AttributeModifierNugget
			Radius="50.0"
			AttributeModifierName="SpecialPower_AlliedAntiNavyShipTech1">
				<SpecialObjectFilter
					Rule="ANY"
					Relationship="SAME_PLAYER">
					<IncludeThing>AlliedWarFactory</IncludeThing>
				</SpecialObjectFilter>
			</AttributeModifierNugget>
		</Nuggets>
	</WeaponTemplate>
	<ObjectCreationList
		id="OCL_ModuleTag_SpecialAbilityUpdate16">
		<CreateObject
			Options="IGNORE_ALL_OBJECTS DO_NOT_COPY_SHADERS"
			Disposition="ON_GROUND_ALIGNED USE_WATER_SURFACE">
			<CreateObject>ModuleTag_SpecialAbilityUpdate16</CreateObject>
		</CreateObject>
	</ObjectCreationList>
	
	<GameObject
		id="ModuleTag_SpecialAbilityUpdate17"
			inheritFrom="BaseUnitBuild">
		<Behaviors>
			<SpecialPower
					 id="ModuleTag_SpecialAbility"
					 SpecialPowerTemplate="SpecialPower_SovietDesolatorInfantry"
					 AvailableAtStart="true"
					 UpdateModuleStartsAttack="true"/>
			<WeaponFireSpecialAbilityUpdate
				id="ModuleTag_SpecialAbilityUpdate"
				SpecialPowerTemplate="SpecialPower_SovietDesolatorInfantry"
				SpecialWeapon="SpecialPower_SovietDesolatorInfantryWeapon"/>
		</Behaviors>
	</GameObject>
	<WeaponTemplate
		id="SpecialPower_SovietDesolatorInfantryWeapon"
		RadiusDamageAffects="ALLIES"
        Flags="NOT_ATTRACTED_BY_MAGNETS"
		RequiredAntiMask="ANTI_STRUCTURE">
		<Nuggets>
			<AttributeModifierNugget
			Radius="50.0"
			AttributeModifierName="SpecialPower_SovietDesolatorInfantry">
				<SpecialObjectFilter
					Rule="ANY"
					Relationship="SAME_PLAYER">
					<IncludeThing>AlliedWarFactory</IncludeThing>
				</SpecialObjectFilter>
			</AttributeModifierNugget>
		</Nuggets>
	</WeaponTemplate>
	<ObjectCreationList
		id="OCL_ModuleTag_SpecialAbilityUpdate17">
		<CreateObject
			Options="IGNORE_ALL_OBJECTS DO_NOT_COPY_SHADERS"
			Disposition="ON_GROUND_ALIGNED USE_WATER_SURFACE">
			<CreateObject>ModuleTag_SpecialAbilityUpdate17</CreateObject>
		</CreateObject>
	</ObjectCreationList>

	<GameObject
		id="ModuleTag_SpecialAbilityUpdate18"
			inheritFrom="BaseUnitBuild">
		<Behaviors>
			<SpecialPower
					 id="ModuleTag_SpecialAbility"
					 SpecialPowerTemplate="SpecialPower_AlliedGunshipAircraft"
					 AvailableAtStart="true"
					 UpdateModuleStartsAttack="true"/>
			<WeaponFireSpecialAbilityUpdate
				id="ModuleTag_SpecialAbilityUpdate"
				SpecialPowerTemplate="SpecialPower_AlliedGunshipAircraft"
				SpecialWeapon="SpecialPower_AlliedGunshipAircraftWeapon"/>
		</Behaviors>
	</GameObject>
	<WeaponTemplate
		id="SpecialPower_AlliedGunshipAircraftWeapon"
		RadiusDamageAffects="ALLIES"
        Flags="NOT_ATTRACTED_BY_MAGNETS"
		RequiredAntiMask="ANTI_STRUCTURE">
		<Nuggets>
			<AttributeModifierNugget
			Radius="50.0"
			AttributeModifierName="SpecialPower_AlliedGunshipAircraft">
				<SpecialObjectFilter
					Rule="ANY"
					Relationship="SAME_PLAYER">
					<IncludeThing>AlliedWarFactory</IncludeThing>
				</SpecialObjectFilter>
			</AttributeModifierNugget>
		</Nuggets>
	</WeaponTemplate>
	<ObjectCreationList
		id="OCL_ModuleTag_SpecialAbilityUpdate18">
		<CreateObject
			Options="IGNORE_ALL_OBJECTS DO_NOT_COPY_SHADERS"
			Disposition="ON_GROUND_ALIGNED USE_WATER_SURFACE">
			<CreateObject>ModuleTag_SpecialAbilityUpdate18</CreateObject>
		</CreateObject>
	</ObjectCreationList>

	<GameObject
		id="ModuleTag_SpecialAbilityUpdate19"
			inheritFrom="BaseUnitBuild">
		<Behaviors>
			<SpecialPower
					 id="ModuleTag_SpecialAbility"
					 SpecialPowerTemplate="SpecialPower_AlliedAntiAirShip"
					 AvailableAtStart="true"
					 UpdateModuleStartsAttack="true"/>
			<WeaponFireSpecialAbilityUpdate
				id="ModuleTag_SpecialAbilityUpdate"
				SpecialPowerTemplate="SpecialPower_AlliedAntiAirShip"
				SpecialWeapon="SpecialPower_AlliedAntiAirShipWeapon"/>
		</Behaviors>
	</GameObject>
	<WeaponTemplate
		id="SpecialPower_AlliedAntiAirShipWeapon"
		RadiusDamageAffects="ALLIES"
        Flags="NOT_ATTRACTED_BY_MAGNETS"
		RequiredAntiMask="ANTI_STRUCTURE">
		<Nuggets>
			<AttributeModifierNugget
			Radius="50.0"
			AttributeModifierName="SpecialPower_AlliedAntiAirShip">
				<SpecialObjectFilter
					Rule="ANY"
					Relationship="SAME_PLAYER">
					<IncludeThing>AlliedWarFactory</IncludeThing>
				</SpecialObjectFilter>
			</AttributeModifierNugget>
		</Nuggets>
	</WeaponTemplate>
	<ObjectCreationList
		id="OCL_ModuleTag_SpecialAbilityUpdate19">
		<CreateObject
			Options="IGNORE_ALL_OBJECTS DO_NOT_COPY_SHADERS"
			Disposition="ON_GROUND_ALIGNED USE_WATER_SURFACE">
			<CreateObject>ModuleTag_SpecialAbilityUpdate19</CreateObject>
		</CreateObject>
	</ObjectCreationList>

	<GameObject
		id="ModuleTag_SpecialAbilityUpdate20"
			inheritFrom="BaseUnitBuild">
		<Behaviors>
			<SpecialPower
					 id="ModuleTag_SpecialAbility"
					 SpecialPowerTemplate="SpecialPower_SovietAntiAirShip"
					 AvailableAtStart="true"
					 UpdateModuleStartsAttack="true"/>
			<WeaponFireSpecialAbilityUpdate
				id="ModuleTag_SpecialAbilityUpdate"
				SpecialPowerTemplate="SpecialPower_SovietAntiAirShip"
				SpecialWeapon="SpecialPower_SovietAntiAirShipWeapon"/>
		</Behaviors>
	</GameObject>
	<WeaponTemplate
		id="SpecialPower_SovietAntiAirShipWeapon"
		RadiusDamageAffects="ALLIES"
        Flags="NOT_ATTRACTED_BY_MAGNETS"
		RequiredAntiMask="ANTI_STRUCTURE">
		<Nuggets>
			<AttributeModifierNugget
			Radius="50.0"
			AttributeModifierName="SpecialPower_SovietAntiAirShip">
				<SpecialObjectFilter
					Rule="ANY"
					Relationship="SAME_PLAYER">
					<IncludeThing>AlliedWarFactory</IncludeThing>
				</SpecialObjectFilter>
			</AttributeModifierNugget>
		</Nuggets>
	</WeaponTemplate>
	<ObjectCreationList
		id="OCL_ModuleTag_SpecialAbilityUpdate20">
		<CreateObject
			Options="IGNORE_ALL_OBJECTS DO_NOT_COPY_SHADERS"
			Disposition="ON_GROUND_ALIGNED USE_WATER_SURFACE">
			<CreateObject>ModuleTag_SpecialAbilityUpdate20</CreateObject>
		</CreateObject>
	</ObjectCreationList>

	<GameObject
		id="ModuleTag_SpecialAbilityUpdate21"
			inheritFrom="BaseUnitBuild">
		<Behaviors>
			<SpecialPower
					 id="ModuleTag_SpecialAbility"
					 SpecialPowerTemplate="SpecialPower_SovietSurveyor"
					 AvailableAtStart="true"
					 UpdateModuleStartsAttack="true"/>
			<WeaponFireSpecialAbilityUpdate
				id="ModuleTag_SpecialAbilityUpdate"
				SpecialPowerTemplate="SpecialPower_SovietSurveyor"
				SpecialWeapon="SpecialPower_SovietSurveyorWeapon"/>
		</Behaviors>
	</GameObject>
	<WeaponTemplate
		id="SpecialPower_SovietSurveyorWeapon"
		RadiusDamageAffects="ALLIES"
        Flags="NOT_ATTRACTED_BY_MAGNETS"
		RequiredAntiMask="ANTI_STRUCTURE">
		<Nuggets>
			<AttributeModifierNugget
			Radius="50.0"
			AttributeModifierName="SpecialPower_SovietSurveyor">
				<SpecialObjectFilter
					Rule="ANY"
					Relationship="SAME_PLAYER">
					<IncludeThing>AlliedWarFactory</IncludeThing>
				</SpecialObjectFilter>
			</AttributeModifierNugget>
		</Nuggets>
	</WeaponTemplate>
	<ObjectCreationList
		id="OCL_ModuleTag_SpecialAbilityUpdate21">
		<CreateObject
			Options="IGNORE_ALL_OBJECTS DO_NOT_COPY_SHADERS"
			Disposition="ON_GROUND_ALIGNED USE_WATER_SURFACE">
			<CreateObject>ModuleTag_SpecialAbilityUpdate21</CreateObject>
		</CreateObject>
	</ObjectCreationList>

	<GameObject
		id="ModuleTag_SpecialAbilityUpdate22"
			inheritFrom="BaseUnitBuild">
		<Behaviors>
			<SpecialPower
					 id="ModuleTag_SpecialAbility"
					 SpecialPowerTemplate="SpecialPower_JapanAntiAirVehicleTech1"
					 AvailableAtStart="true"
					 UpdateModuleStartsAttack="true"/>
			<WeaponFireSpecialAbilityUpdate
				id="ModuleTag_SpecialAbilityUpdate"
				SpecialPowerTemplate="SpecialPower_JapanAntiAirVehicleTech1"
				SpecialWeapon="SpecialPower_JapanAntiAirVehicleTech1Weapon"/>
		</Behaviors>
	</GameObject>
	<WeaponTemplate
		id="SpecialPower_JapanAntiAirVehicleTech1Weapon"
		RadiusDamageAffects="ALLIES"
        Flags="NOT_ATTRACTED_BY_MAGNETS"
		RequiredAntiMask="ANTI_STRUCTURE">
		<Nuggets>
			<AttributeModifierNugget
			Radius="50.0"
			AttributeModifierName="SpecialPower_JapanAntiAirVehicleTech1">
				<SpecialObjectFilter
					Rule="ANY"
					Relationship="SAME_PLAYER">
					<IncludeThing>AlliedWarFactory</IncludeThing>
				</SpecialObjectFilter>
			</AttributeModifierNugget>
		</Nuggets>
	</WeaponTemplate>
	<ObjectCreationList
		id="OCL_ModuleTag_SpecialAbilityUpdate22">
		<CreateObject
			Options="IGNORE_ALL_OBJECTS DO_NOT_COPY_SHADERS"
			Disposition="ON_GROUND_ALIGNED USE_WATER_SURFACE">
			<CreateObject>ModuleTag_SpecialAbilityUpdate22</CreateObject>
		</CreateObject>
	</ObjectCreationList>

	<GameObject
		id="ModuleTag_SpecialAbilityUpdate23"
			inheritFrom="BaseUnitBuild">
		<Behaviors>
			<SpecialPower
					 id="ModuleTag_SpecialAbility"
					 SpecialPowerTemplate="SpecialPower_JapanSentinelVehicle"
					 AvailableAtStart="true"
					 UpdateModuleStartsAttack="true"/>
			<WeaponFireSpecialAbilityUpdate
				id="ModuleTag_SpecialAbilityUpdate"
				SpecialPowerTemplate="SpecialPower_JapanSentinelVehicle"
				SpecialWeapon="SpecialPower_JapanSentinelVehicleWeapon"/>
		</Behaviors>
	</GameObject>
	<WeaponTemplate
		id="SpecialPower_JapanSentinelVehicleWeapon"
		RadiusDamageAffects="ALLIES"
        Flags="NOT_ATTRACTED_BY_MAGNETS"
		RequiredAntiMask="ANTI_STRUCTURE">
		<Nuggets>
			<AttributeModifierNugget
			Radius="50.0"
			AttributeModifierName="SpecialPower_JapanSentinelVehicle">
				<SpecialObjectFilter
					Rule="ANY"
					Relationship="SAME_PLAYER">
					<IncludeThing>AlliedWarFactory</IncludeThing>
				</SpecialObjectFilter>
			</AttributeModifierNugget>
		</Nuggets>
	</WeaponTemplate>
	<ObjectCreationList
		id="OCL_ModuleTag_SpecialAbilityUpdate23">
		<CreateObject
			Options="IGNORE_ALL_OBJECTS DO_NOT_COPY_SHADERS"
			Disposition="ON_GROUND_ALIGNED USE_WATER_SURFACE">
			<CreateObject>ModuleTag_SpecialAbilityUpdate23</CreateObject>
		</CreateObject>
	</ObjectCreationList>

	<GameObject
		id="ModuleTag_SpecialAbilityUpdate24"
			inheritFrom="BaseUnitBuild">
		<Behaviors>
			<SpecialPower
					 id="ModuleTag_SpecialAbility"
					 SpecialPowerTemplate="SpecialPower_JapanAntiInfantryVehicle"
					 AvailableAtStart="true"
					 UpdateModuleStartsAttack="true"/>
			<WeaponFireSpecialAbilityUpdate
				id="ModuleTag_SpecialAbilityUpdate"
				SpecialPowerTemplate="SpecialPower_JapanAntiInfantryVehicle"
				SpecialWeapon="SpecialPower_JapanAntiInfantryVehicleWeapon"/>
		</Behaviors>
	</GameObject>
	<WeaponTemplate
		id="SpecialPower_JapanAntiInfantryVehicleWeapon"
		RadiusDamageAffects="ALLIES"
        Flags="NOT_ATTRACTED_BY_MAGNETS"
		RequiredAntiMask="ANTI_STRUCTURE">
		<Nuggets>
			<AttributeModifierNugget
			Radius="50.0"
			AttributeModifierName="SpecialPower_JapanAntiInfantryVehicle">
				<SpecialObjectFilter
					Rule="ANY"
					Relationship="SAME_PLAYER">
					<IncludeThing>AlliedWarFactory</IncludeThing>
				</SpecialObjectFilter>
			</AttributeModifierNugget>
		</Nuggets>
	</WeaponTemplate>
	<ObjectCreationList
		id="OCL_ModuleTag_SpecialAbilityUpdate24">
		<CreateObject
			Options="IGNORE_ALL_OBJECTS DO_NOT_COPY_SHADERS"
			Disposition="ON_GROUND_ALIGNED USE_WATER_SURFACE">
			<CreateObject>ModuleTag_SpecialAbilityUpdate24</CreateObject>
		</CreateObject>
	</ObjectCreationList>
	
	<GameObject
		id="ModuleTag_SpecialAbilityUpdateMiner"
			inheritFrom="BaseUnitBuild">
		<Behaviors>
			<SpecialPower
					 id="ModuleTag_SpecialAbility"
					 SpecialPowerTemplate="SpecialPower_AlliedMiner"
					 AvailableAtStart="true"
					 UpdateModuleStartsAttack="true"/>
			<WeaponFireSpecialAbilityUpdate
				id="ModuleTag_SpecialAbilityUpdate"
				SpecialPowerTemplate="SpecialPower_AlliedMiner"
				SpecialWeapon="SpecialPower_AlliedMinerWeapon"/>
		</Behaviors>
	</GameObject>
	<WeaponTemplate
		id="SpecialPower_AlliedMinerWeapon"
		RadiusDamageAffects="ALLIES"
        Flags="NOT_ATTRACTED_BY_MAGNETS"
		RequiredAntiMask="ANTI_STRUCTURE">
		<Nuggets>
			<AttributeModifierNugget
			Radius="50.0"
			AttributeModifierName="SpecialPower_AlliedMiner">
				<SpecialObjectFilter
					Rule="ANY"
					Relationship="SAME_PLAYER">
					<IncludeThing>AlliedWarFactory</IncludeThing>
				</SpecialObjectFilter>
			</AttributeModifierNugget>
		</Nuggets>
	</WeaponTemplate>
	<ObjectCreationList
		id="OCL_ModuleTag_SpecialAbilityUpdateMiner">
		<CreateObject
			Options="IGNORE_ALL_OBJECTS DO_NOT_COPY_SHADERS"
			Disposition="ON_GROUND_ALIGNED USE_WATER_SURFACE">
			<CreateObject>ModuleTag_SpecialAbilityUpdateMiner</CreateObject>
		</CreateObject>
	</ObjectCreationList>

	<WeaponTemplate
		id="DamageSelfAlliedWarFactoryWarhead"
		AttackRange="1000.0"
		RequiredAntiMask="ANTI_GROUND ANTI_STRUCTURE ANTI_WATER"
		AcceptableAimDelta="180d"
		CanFireWhileMoving="true"
		RadiusDamageAffects="ALLIES"
        Flags="NOT_ATTRACTED_BY_MAGNETS">
		<Nuggets>
			<DamageNugget
				Damage="100.0"
				Radius="50.0"
				DamageType="MAGIC"
				DeathType="SUICIDED">
				<SpecialObjectFilter
					Rule="ANY"
					Relationship="SAME_PLAYER">
					<IncludeThing>ChooseUnitStructure</IncludeThing>
					<IncludeThing>ChooseUnitStructureAI</IncludeThing>
				</SpecialObjectFilter>
			</DamageNugget>
		</Nuggets>
	</WeaponTemplate>
</AssetDeclaration>